MANIFEST.in
RELEASE-VERSION
pavement.py
paver-minilib.zip
setup.py
version.py
c_array_defs/__init__.py
c_array_defs.egg-info/PKG-INFO
c_array_defs.egg-info/SOURCES.txt
c_array_defs.egg-info/dependency_links.txt
c_array_defs.egg-info/top_level.txt
c_array_defs/Arduino/CArrayDefs/CArrayDefs.h
c_array_defs/lib/C-Array-Defs.tar.gz