Metadata-Version: 1.0
Name: c-array-defs
Version: 0.1.post2
Summary: Simple C classes for arrays of standard numeric types.
Home-page: https://github.com/wheeler-microfluidics/c-array-defs
Author: Christian Fobel
Author-email: christian@fobel.net
License: GPL
Keywords: c++ array simple
Platform: UNKNOWN
